poke-harry/__init__.py
poke-harry/pokemon.csv
poke-harry/random_pokemon.py
poke-harrysemi/__init__.py
poke-harrysemi/pokemon.csv
poke-harrysemi/random_pokemon.py
pokesemi/__init__.py
pokesemi/pokemon.csv
pokesemi/random_pokemon.py
pokesemi-1.0.1.dist-info/METADATA
pokesemi-1.0.1.dist-info/WHEEL
pokesemi-1.0.1.dist-info/top_level.txt
pokesemi-1.0.1.dist-info/RECORD
