Metadata-Version: 2.1
Name: pokesemi
Version: 1.0.1
Summary: una biblioteca que contiene la clase llamada RandomPOkemonpara generar un pokemon aleatorio
Author: Semiramis Del Castillo
Author-email: 202224131_galicia@tesch.edu.mx
Requires-Dist: pandas
